<opus_project>
  <general>
    <description type="string">Sample Eugene project</description>
    <project_name flags="hidden" hidden="True" type="string">eugene_gridcell</project_name>
    <parent type="file">urbansim_gridcell/configs/urbansim_gridcell.xml</parent>
    <dataset_pool_configuration type="class">
      <Class_name hidden="True" type="string">DatasetPoolConfiguration</Class_name>
      <Class_path hidden="True" type="string">opus_core.configurations.dataset_pool_configuration</Class_path>
      <package_order type="list">['eugene', 'urbansim', 'opus_core']</package_order>
    </dataset_pool_configuration>
  </general>
  <model_manager>
    <model_system setexpanded="True" type="model_system">
      <estimation_config type="configuration">
        <cache_directory parser_action="prefix_with_opus_data_path" type="directory">eugene_gridcell/base_year_data</cache_directory>
        <estimation_database_configuration type="class">
          <Class_name hidden="True" type="string">EstimationDatabaseConfiguration</Class_name>
          <Class_path hidden="True" type="string">opus_core.database_management.configurations.estimation_database_configuration</Class_path>
          <database_name type="string" />
        </estimation_database_configuration>
        <datasets_to_preload parser_action="list_to_dictionary" type="selectable_list">
          <gridcell choices="Load|Skip" copyable="True" followers="my_dataset" type="dataset">Load</gridcell>
        </datasets_to_preload>
        <dataset_pool_configuration type="class">
          <Class_name hidden="True" type="string">DatasetPoolConfiguration</Class_name>
          <Class_path hidden="True" type="string">opus_core.configurations.dataset_pool_configuration</Class_path>
          <package_order type="list">['eugene', 'urbansim', 'opus_core']</package_order>
          <package_order_exceptions type="dictionary" />
        </dataset_pool_configuration>
        <datasets_to_cache_after_each_model type="list">[]</datasets_to_cache_after_each_model>
        <low_memory_mode type="boolean">False</low_memory_mode>
        <base_year type="integer">1980</base_year>
        <years type="tuple">
          <firstyear type="integer">1980</firstyear>
          <lastyear type="integer">1980</lastyear>
        </years>
        <save_estimation_results choices="True|False" type="boolean">True</save_estimation_results>
      </estimation_config>
      <regression_model copyable="True" type="model">
        <specification type="dictionary">
          <submodel copyable="True" type="submodel">
            <description type="string">No submodel</description>
            <submodel_id type="integer">-2</submodel_id>
            <variables type="variable_list">population</variables>
          </submodel>
        </specification>
        <structure type="dictionary">
          <import type="dictionary">
            <opus_core.regression_model type="string">RegressionModel</opus_core.regression_model>
          </import>
          <init type="dictionary">
            <name type="string">RegressionModel</name>
            <regression_procedure type="quoted_string">opus_core.linear_regression</regression_procedure>
            <submodel_string parser_action="blank_to_None" type="string" />
            <run_config parser_action="blank_to_None" type="string" />
            <estimate_config parser_action="blank_to_None" type="string" />
            <debuglevel type="integer">0</debuglevel>
            <dataset_pool type="string">dataset_pool</dataset_pool>
          </init>
          <run type="dictionary">
            <specification type="string">specification</specification>
            <coefficients type="string">coefficients</coefficients>
            <dataset type="string">gridcell</dataset>
            <index parser_action="blank_to_None" type="string">rm_index</index>
            <chunk_specification parser_action="blank_to_None" type="string" />
            <data_objects type="string">datasets</data_objects>
          </run>
          <prepare_for_run type="dictionary">
            <name type="string">prepare_for_run</name>
            <dataset parser_action="blank_to_None" type="string" />
            <dataset_filter parser_action="blank_to_None" type="quoted_string" />
            <specification_storage type="string">base_cache_storage</specification_storage>
            <specification_table type="quoted_string">regression_model_specification</specification_table>
            <coefficients_storage type="string">base_cache_storage</coefficients_storage>
            <coefficients_table type="quoted_string">regression_model_coefficients_table</coefficients_table>
            <sample_coefficients type="boolean">False</sample_coefficients>
            <cache_storage type="string">base_cache_storage</cache_storage>
            <multiplicator type="integer">1</multiplicator>
            <output type="string">(specification, coefficients, rm_index)</output>
          </prepare_for_run>
          <estimate type="dictionary">
            <specification type="string">specification</specification>
            <dataset type="string">gridcell</dataset>
            <dependent_variable config_name="outcome_attribute" type="quoted_string">population</dependent_variable>
            <index parser_action="blank_to_None" type="string">rm_index</index>
            <procedure type="quoted_string">opus_core.estimate_linear_regression</procedure>
            <data_objects type="string">datasets</data_objects>
            <output type="string">(coefficients, dummy)</output>
          </estimate>
          <prepare_for_estimate type="dictionary">
            <name type="string">prepare_for_estimate</name>
            <dataset parser_action="blank_to_None" type="string" />
            <dataset_filter parser_action="blank_to_None" type="quoted_string" />
            <specification_storage type="string">base_cache_storage</specification_storage>
            <specification_table type="quoted_string">regression_model_specification</specification_table>
            <output type="string">(specification, rm_index)</output>
          </prepare_for_estimate>
        </structure>
      </regression_model>
      <simple_model_template copyable="True" hidden="True" type="model_template">
        <specification type="dictionary" />
        <structure type="dictionary">
          <import type="dictionary">
            <opus_core.simple_model type="string">SimpleModel</opus_core.simple_model>
          </import>
          <init type="dictionary">
            <name type="string">SimpleModel</name>
          </init>
          <run type="dictionary">
            <dataset type="string">fill in</dataset>
            <expression type="quoted_string">fill in</expression>
            <outcome_attribute parser_action="blank_to_None" type="quoted_string" />
            <dataset_pool type="string">dataset_pool</dataset_pool>
          </run>
          <prepare_for_run type="dictionary" />
          <estimate type="dictionary" />
          <prepare_for_estimate type="dictionary" />
        </structure>
      </simple_model_template>
      <choice_model_template copyable="True" hidden="True" type="model_template">
        <specification type="dictionary" />
        <structure type="dictionary">
          <import type="dictionary">
            <opus_core.choice_model type="string">ChoiceModel</opus_core.choice_model>
          </import>
          <init type="dictionary">
            <name type="string">ChoiceModel</name>
            <choice_set type="string">fill in</choice_set>
            <utilities type="quoted_string">opus_core.linear_utilities</utilities>
            <probabilities type="quoted_string">opus_core.mnl_probabilities</probabilities>
            <choices type="quoted_string">opus_core.random_choices</choices>
            <submodel_string parser_action="blank_to_None" type="string" />
            <choice_attribute_name type="quoted_string">choice_id</choice_attribute_name>
            <interaction_pkg type="quoted_string">opus_core</interaction_pkg>
            <run_config parser_action="blank_to_None" type="string" />
            <estimate_config type="dictionary">
              <estimation_size_agents type="float">1.0</estimation_size_agents>
            </estimate_config>
            <debuglevel type="integer">0</debuglevel>
            <dataset_pool type="string">dataset_pool</dataset_pool>
          </init>
          <run type="dictionary">
            <specification type="string">specification</specification>
            <coefficients type="string">coefficients</coefficients>
            <agent_set type="string">fill in</agent_set>
            <agents_index type="string">cm_index</agents_index>
            <chunk_specification parser_action="blank_to_None" type="string" />
            <data_objects type="string">datasets</data_objects>
          </run>
          <prepare_for_run type="dictionary">
            <name type="string">prepare_for_run</name>
            <agent_set parser_action="blank_to_None" type="string" />
            <agent_filter parser_action="blank_to_None" type="quoted_string" />
            <specification_storage type="string">base_cache_storage</specification_storage>
            <specification_table type="quoted_string">choice_model_template_specification</specification_table>
            <coefficients_storage type="string">base_cache_storage</coefficients_storage>
            <coefficients_table type="quoted_string">choice_model_template_coefficients</coefficients_table>
            <sample_coefficients type="boolean">False</sample_coefficients>
            <cache_storage type="string">base_cache_storage</cache_storage>
            <multiplicator type="integer">1</multiplicator>
            <output type="string">(specification, coefficients, cm_index)</output>
          </prepare_for_run>
          <estimate type="dictionary">
            <specification type="string">specification</specification>
            <agent_set type="string">fill in</agent_set>
            <agents_index type="string">cm_index</agents_index>
            <procedure type="quoted_string">opus_core.bhhh_mnl_estimation</procedure>
            <data_objects type="string">datasets</data_objects>
            <output type="string">(coefficients, dummy)</output>
          </estimate>
          <prepare_for_estimate type="dictionary">
            <name type="string">prepare_for_estimate</name>
            <agent_set parser_action="blank_to_None" type="string" />
            <agent_filter parser_action="blank_to_None" type="quoted_string" />
            <specification_storage type="string">base_cache_storage</specification_storage>
            <specification_table type="quoted_string">choice_model_template_specification</specification_table>
            <output type="string">(specification, cm_index)</output>
          </prepare_for_estimate>
        </structure>
      </choice_model_template>
      <regression_model_template copyable="True" hidden="True" type="model_template">
        <specification type="dictionary" />
        <structure type="dictionary">
          <import type="dictionary">
            <opus_core.regression_model type="string">RegressionModel</opus_core.regression_model>
          </import>
          <init type="dictionary">
            <name type="string">RegressionModel</name>
            <regression_procedure type="quoted_string">opus_core.linear_regression</regression_procedure>
            <submodel_string parser_action="blank_to_None" type="string" />
            <run_config parser_action="blank_to_None" type="string" />
            <estimate_config parser_action="blank_to_None" type="string" />
            <debuglevel type="integer">0</debuglevel>
            <dataset_pool type="string">dataset_pool</dataset_pool>
          </init>
          <run type="dictionary">
            <specification type="string">specification</specification>
            <coefficients type="string">coefficients</coefficients>
            <dataset type="string">fill in</dataset>
            <index hidden="True" parser_action="blank_to_None" type="string">rm_index</index>
            <data_objects type="string">datasets</data_objects>
          </run>
          <prepare_for_run type="dictionary">
            <name type="string">prepare_for_run</name>
            <dataset parser_action="blank_to_None" type="string" />
            <dataset_filter parser_action="blank_to_None" type="quoted_string" />
            <specification_storage type="string">base_cache_storage</specification_storage>
            <specification_table type="quoted_string">regression_model_template_specification</specification_table>
            <coefficients_storage type="string">base_cache_storage</coefficients_storage>
            <coefficients_table type="quoted_string">regression_model_template_coefficients</coefficients_table>
            <sample_coefficients type="boolean">False</sample_coefficients>
            <cache_storage type="string">base_cache_storage</cache_storage>
            <multiplicator type="integer">1</multiplicator>
            <output type="string">(specification, coefficients, rm_index)</output>
          </prepare_for_run>
          <estimate type="dictionary">
            <specification type="string">specification</specification>
            <dataset type="string">fill in</dataset>
            <dependent_variable config_name="outcome_attribute" type="quoted_string">fill in</dependent_variable>
            <index parser_action="blank_to_None" type="string">rm_index</index>
            <procedure type="quoted_string">opus_core.estimate_linear_regression</procedure>
            <data_objects type="string">datasets</data_objects>
            <output type="string">(coefficients, dummy)</output>
          </estimate>
          <prepare_for_estimate type="dictionary">
            <name type="string">prepare_for_estimate</name>
            <dataset parser_action="blank_to_None" type="string" />
            <dataset_filter parser_action="blank_to_None" type="quoted_string" />
            <specification_storage type="string">base_cache_storage</specification_storage>
            <specification_table type="quoted_string">regression_model_template_specification</specification_table>
            <output type="string">(specification, rm_index)</output>
          </prepare_for_estimate>
        </structure>
      </regression_model_template>
      <allocation_model_template copyable="True" hidden="True" type="model_template">
        <specification type="dictionary" />
        <structure type="dictionary">
          <import type="dictionary">
            <opus_core.allocation_model type="string">AllocationModel</opus_core.allocation_model>
          </import>
          <init type="dictionary">
            <name type="string">AllocationModel</name>
          </init>
          <run type="dictionary">
            <dataset type="string">fill in</dataset>
            <outcome_attribute type="quoted_string">fill in</outcome_attribute>
            <weight_attribute type="quoted_string">fill in</weight_attribute>
            <control_totals type="string">cts</control_totals>
            <current_year type="string">year</current_year>
            <control_total_attribute type="quoted_string">fill in</control_total_attribute>
            <year_attribute type="quoted_string">year</year_attribute>
            <capacity_attribute parser_action="blank_to_None" type="quoted_string" />
            <dataset_pool type="string">dataset_pool</dataset_pool>
          </run>
          <prepare_for_run type="dictionary">
            <name type="string">prepare_for_run</name>
            <storage type="string">base_cache_storage</storage>
            <control_totals_table_name type="quoted_string">fill in</control_totals_table_name>
            <control_totals_id_name type="list">['year']</control_totals_id_name>
            <control_totals_dataset_name type="quoted_string">control_totals</control_totals_dataset_name>
            <output type="string">cts</output>
          </prepare_for_run>
          <estimate type="dictionary" />
          <prepare_for_estimate type="dictionary" />
        </structure>
      </allocation_model_template>
      <agent_location_choice_model_template copyable="True" hidden="True" type="model_template">
        <specification type="dictionary" />
        <structure type="dictionary">
          <import type="dictionary">
            <urbansim.models.agent_location_choice_model type="string">AgentLocationChoiceModel</urbansim.models.agent_location_choice_model>
          </import>
          <init type="dictionary">
            <name type="string">AgentLocationChoiceModel</name>
            <location_set type="string">fill in</location_set>
            <sampler type="quoted_string">opus_core.samplers.weighted_sampler</sampler>
            <utilities type="quoted_string">opus_core.linear_utilities</utilities>
            <probabilities type="quoted_string">opus_core.mnl_probabilities</probabilities>
            <choices type="quoted_string">urbansim.lottery_choices</choices>
            <filter parser_action="blank_to_None" type="quoted_string" />
            <submodel_string parser_action="blank_to_None" type="quoted_string" />
            <location_id_string parser_action="blank_to_None" type="quoted_string" />
            <dataset_pool type="string">dataset_pool</dataset_pool>
            <model_name type="quoted_string">AgentLocationChoiceModel</model_name>
            <short_name type="quoted_string">ALCM</short_name>
            <variable_package type="quoted_string">urbansim</variable_package>
            <debuglevel type="string">debuglevel</debuglevel>
            <run_config type="dictionary">
              <sample_size_locations type="integer">30</sample_size_locations>
              <sample_proportion_locations parser_action="blank_to_None" type="integer" />
              <compute_capacity_flag type="boolean">True</compute_capacity_flag>
              <capacity_string parser_action="blank_to_None" type="quoted_string" />
              <number_of_units_string parser_action="blank_to_None" type="quoted_string" />
              <number_of_agents_string parser_action="blank_to_None" type="quoted_string" />
              <lottery_max_iterations type="integer">3</lottery_max_iterations>
            </run_config>
            <estimate_config type="dictionary">
              <weights_for_estimation_string parser_action="blank_to_None" type="quoted_string" />
              <sample_size_locations type="integer">30</sample_size_locations>
              <sample_proportion_locations parser_action="blank_to_None" type="integer" />
              <estimation_size_agents type="float">1.0</estimation_size_agents>
            </estimate_config>
          </init>
          <prepare_for_estimate type="dictionary">
            <name type="string">prepare_for_estimate</name>
            <output type="string">(alcm_specification, alcm_index)</output>
            <specification_storage type="string">base_cache_storage</specification_storage>
            <specification_table type="quoted_string">agent_location_choice_model_specification</specification_table>
            <agent_set type="string">fill in</agent_set>
            <agents_for_estimation_storage type="string">base_cache_storage</agents_for_estimation_storage>
            <agents_for_estimation_table type="quoted_string">fill in</agents_for_estimation_table>
            <data_objects type="string">datasets</data_objects>
            <index_to_unplace parser_action="blank_to_None" type="string" />
            <join_datasets choices="True|False" type="boolean">True</join_datasets>
            <portion_to_unplace type="string">1.0</portion_to_unplace>
            <filter parser_action="blank_to_None" type="quoted_string" />
            <location_id_variable parser_action="blank_to_None" type="quoted_string" />
          </prepare_for_estimate>
          <estimate type="dictionary">
            <output type="string">(alcm_coefficients, dummy)</output>
            <agent_set type="string">fill in</agent_set>
            <agents_index type="string">alcm_index</agents_index>
            <procedure type="quoted_string">opus_core.bhhh_mnl_estimation</procedure>
            <data_objects type="string">datasets</data_objects>
            <debuglevel type="string">debuglevel</debuglevel>
            <specification type="string">alcm_specification</specification>
          </estimate>
          <prepare_for_run type="dictionary">
            <name type="string">prepare_for_run</name>
            <output type="string">(alcm_specification, alcm_coefficients)</output>
            <coefficients_storage type="string">base_cache_storage</coefficients_storage>
            <coefficients_table type="quoted_string">agent_location_choice_model_coefficients</coefficients_table>
            <specification_storage type="string">base_cache_storage</specification_storage>
            <specification_table type="quoted_string">agent_location_choice_model_specification</specification_table>
          </prepare_for_run>
          <run type="dictionary">
            <agent_set type="string">fill in</agent_set>
            <agents_index parser_action="blank_to_None" type="string" />
            <chunk_specification type="string">{'records_per_chunk':50000}</chunk_specification>
            <coefficients type="string">alcm_coefficients</coefficients>
            <data_objects type="string">datasets</data_objects>
            <debuglevel type="string">debuglevel</debuglevel>
            <specification type="string">alcm_specification</specification>
            <maximum_runs type="integer">10</maximum_runs>
          </run>
        </structure>
      </agent_location_choice_model_template>
      <basic_estimation_template copyable="True" hidden="True" type="estimation_template">
        <submodel copyable="True" type="submodel">
          <description type="string">No submodel</description>
          <submodel_id type="integer">-2</submodel_id>
          <variables type="variable_list">var1</variables>
        </submodel>
      </basic_estimation_template>
      <choice_model_with_equations_estimation_template copyable="True" hidden="True" type="estimation_template">
        <submodel copyable="True" type="submodel">
          <description type="string">No submodel</description>
          <submodel_id type="integer">-2</submodel_id>
          <choice_1 copyable="True" type="dictionary">
            <equation_id type="integer">1</equation_id>
            <variables type="variable_list">constant</variables>
          </choice_1>
          <choice_2 copyable="True" type="dictionary">
            <equation_id type="integer">2</equation_id>
            <variables type="variable_list">var1</variables>
          </choice_2>
        </submodel>
      </choice_model_with_equations_estimation_template>
    </model_system>
    </model_manager>
  <scenario_manager>
    <Eugene_baseline copyable="True" executable="True" setexpanded="True" type="scenario">
      <parent type="scenario_name">default_scenario</parent>
      <base_year type="integer">1980</base_year>
      <years_to_run config_name="years" type="tuple">
        <firstyear type="integer">1981</firstyear>
        <lastyear type="integer">1981</lastyear>
      </years_to_run>
      <models_to_run config_name="models" type="selectable_list">
        <prescheduled_events choices="Run|Skip" type="model_choice">Run</prescheduled_events>
        <events_coordinator choices="Run|Skip" type="model_choice">Run</events_coordinator>
        <residential_land_share_model choices="Run|Skip" type="model_choice">Run</residential_land_share_model>
        <land_price_model choices="Run|Skip" type="model_choice">Run</land_price_model>
        <development_project_transition_model choices="Run|Skip" type="model_choice">Run</development_project_transition_model>
        <residential_development_project_location_choice_model choices="Run|Skip" type="model_choice">Run</residential_development_project_location_choice_model>
        <commercial_development_project_location_choice_model choices="Run|Skip" type="model_choice">Run</commercial_development_project_location_choice_model>
        <industrial_development_project_location_choice_model choices="Run|Skip" type="model_choice">Run</industrial_development_project_location_choice_model>
        <development_event_transition_model choices="Run|Skip" type="model_choice">Run</development_event_transition_model>
        <events_coordinator choices="Run|Skip" type="model_choice">Run</events_coordinator>
        <residential_land_share_model choices="Run|Skip" type="model_choice">Run</residential_land_share_model>
        <household_transition_model choices="Run|Skip" type="model_choice">Run</household_transition_model>
        <employment_transition_model choices="Run|Skip" type="model_choice">Run</employment_transition_model>
        <household_relocation_model choices="Run|Skip" type="model_choice">Run</household_relocation_model>
        <household_location_choice_model choices="Run|Skip" type="model_choice">Run</household_location_choice_model>
        <employment_relocation_model choices="Run|Skip" type="model_choice">Run</employment_relocation_model>
        <employment_location_choice_model choices="Run|Skip" type="model_choice">Run<group_members type="string">_all_</group_members>
        </employment_location_choice_model>
        <distribute_unplaced_jobs_model choices="Run|Skip" type="model_choice">Run</distribute_unplaced_jobs_model>
      </models_to_run>
      <baseyear_database_configuration config_name="scenario_database_configuration" type="class">
        <Class_name hidden="True" type="string">ScenarioDatabaseConfiguration</Class_name>
        <Class_path hidden="True" type="string">opus_core.database_management.configurations.scenario_database_configuration</Class_path>
        <database_name type="string">eugene_1980_baseyear</database_name>
      </baseyear_database_configuration>
      <cache_directory parser_action="prefix_with_opus_data_path" type="directory">eugene_gridcell/base_year_data</cache_directory>
      <creating_baseyear_cache_configuration type="class">
        <Class_name hidden="True" type="string">CreatingBaseyearCacheConfiguration</Class_name>
        <Class_path hidden="True" type="string">urbansim.configurations.creating_baseyear_cache_configuration</Class_path>
        <scenario_runs_directory config_name="cache_directory_root" parser_action="prefix_with_opus_data_path" type="directory">eugene_gridcell/runs</scenario_runs_directory>
        <scenario_runs_directory config_name="cache_directory_root" parser_action="prefix_with_opus_data_path" type="directory">seattle_parcel/runs</scenario_runs_directory>
        <cache_directory_root config_name="cache_directory_root" parser_action="prefix_with_opus_data_path" type="directory">eugene_gridcell/runs</cache_directory_root>
        <cache_from_database choices="True|False" type="boolean">False</cache_from_database>
        <baseyear_cache type="class">
          <Class_name hidden="True" type="string">BaseyearCacheConfiguration</Class_name>
          <Class_path hidden="True" type="string">opus_core.configurations.baseyear_cache_configuration</Class_path>
          <existing_cache_to_copy parser_action="prefix_with_opus_data_path" type="directory">eugene_gridcell/base_year_data</existing_cache_to_copy>
        </baseyear_cache>
        <cache_scenario_database type="string">urbansim.model_coordinators.cache_scenario_database</cache_scenario_database>
        <tables_to_cache type="selectable_list">
          <annual_employment_control_totals choices="Cache|Skip" type="table">Cache</annual_employment_control_totals>
          <annual_household_control_totals choices="Cache|Skip" type="table">Cache</annual_household_control_totals>
          <buildings choices="Cache|Skip" type="table">Cache</buildings>
          <building_types choices="Cache|Skip" type="table">Cache</building_types>
          <development_event_history choices="Cache|Skip" type="table">Cache</development_event_history>
          <gridcells choices="Cache|Skip" type="table">Cache</gridcells>
          <households choices="Cache|Skip" type="table">Cache</households>
          <job_building_types choices="Cache|Skip" type="table">Cache</job_building_types>
          <jobs choices="Cache|Skip" type="table">Cache</jobs>
          <travel_data choices="Cache|Skip" type="table">Cache</travel_data>
          <zones choices="Cache|Skip" type="table">Cache</zones>
          <counties choices="Cache|Skip" type="table">Cache</counties>
          <commercial_development_location_choice_model_coefficients choices="Cache|Skip" type="table">Cache</commercial_development_location_choice_model_coefficients>
          <commercial_development_location_choice_model_specification choices="Cache|Skip" type="table">Cache</commercial_development_location_choice_model_specification>
          <commercial_employment_location_choice_model_coefficients choices="Cache|Skip" type="table">Cache</commercial_employment_location_choice_model_coefficients>
          <commercial_employment_location_choice_model_specification choices="Cache|Skip" type="table">Cache</commercial_employment_location_choice_model_specification>
          <home_based_employment_location_choice_model_specification choices="Cache|Skip" type="table">Cache</home_based_employment_location_choice_model_specification>
          <home_based_employment_location_choice_model_coefficients choices="Cache|Skip" type="table">Cache</home_based_employment_location_choice_model_coefficients>
          <industrial_employment_location_choice_model_coefficients choices="Cache|Skip" type="table">Cache</industrial_employment_location_choice_model_coefficients>
          <industrial_employment_location_choice_model_specification choices="Cache|Skip" type="table">Cache</industrial_employment_location_choice_model_specification>
          <industrial_development_location_choice_model_coefficients choices="Cache|Skip" type="table">Cache</industrial_development_location_choice_model_coefficients>
          <industrial_development_location_choice_model_specification choices="Cache|Skip" type="table">Cache</industrial_development_location_choice_model_specification>
          <residential_development_location_choice_model_coefficients choices="Cache|Skip" type="table">Cache</residential_development_location_choice_model_coefficients>
          <residential_development_location_choice_model_specification choices="Cache|Skip" type="table">Cache</residential_development_location_choice_model_specification>
          <fazes choices="Cache|Skip" type="table">Skip</fazes>
          <urbansim_constants choices="Cache|Skip" type="table">Cache</urbansim_constants>
          <household_location_choice_model_coefficients choices="Cache|Skip" type="table">Cache</household_location_choice_model_coefficients>
          <household_location_choice_model_specification choices="Cache|Skip" type="table">Cache</household_location_choice_model_specification>
          <land_price_model_coefficients choices="Cache|Skip" type="table">Cache</land_price_model_coefficients>
          <land_price_model_specification choices="Cache|Skip" type="table">Cache</land_price_model_specification>
          <residential_land_share_model_coefficients choices="Cache|Skip" type="table">Cache</residential_land_share_model_coefficients>
          <residential_land_share_model_specification choices="Cache|Skip" type="table">Cache</residential_land_share_model_specification>
          <plan_type_group_definitions choices="Cache|Skip" type="table">Skip</plan_type_group_definitions>
          <plan_type_groups choices="Cache|Skip" type="table">Skip</plan_type_groups>
          <large_areas choices="Cache|Skip" type="table">Skip</large_areas>
          <household_characteristics_for_ht choices="Cache|Skip" type="table">Cache</household_characteristics_for_ht>
          <development_types choices="Cache|Skip" type="table">Cache</development_types>
          <development_type_group_definitions choices="Cache|Skip" type="table">Cache</development_type_group_definitions>
          <development_constraints choices="Cache|Skip" type="table">Cache</development_constraints>
          <annual_relocation_rates_for_households choices="Cache|Skip" type="table">Cache</annual_relocation_rates_for_households>
          <annual_relocation_rates_for_jobs choices="Cache|Skip" type="table">Cache</annual_relocation_rates_for_jobs>
          <base_year choices="Cache|Skip" type="table">Cache</base_year>
          <cities choices="Cache|Skip" type="table">Cache</cities>
          <development_events choices="Cache|Skip" type="table">Skip</development_events>
          <development_type_groups choices="Cache|Skip" type="table">Cache</development_type_groups>
          <employment_adhoc_sector_group_definitions choices="Cache|Skip" type="table">Cache</employment_adhoc_sector_group_definitions>
          <employment_adhoc_sector_groups choices="Cache|Skip" type="table">Cache</employment_adhoc_sector_groups>
          <employment_events choices="Cache|Skip" type="table">Cache</employment_events>
          <employment_sectors choices="Cache|Skip" type="table">Cache</employment_sectors>
          <land_use_events choices="Cache|Skip" type="table">Skip</land_use_events>
          <plan_types choices="Cache|Skip" type="table">Cache</plan_types>
          <race_names choices="Cache|Skip" type="table">Cache</race_names>
          <target_vacancies choices="Cache|Skip" type="table">Cache</target_vacancies>
          <jobs_for_estimation choices="Cache|Skip" type="table">Cache</jobs_for_estimation>
          <households_for_estimation choices="Cache|Skip" type="table">Cache</households_for_estimation>
          <development_events_exogenous choices="Cache|Skip" type="table">Skip</development_events_exogenous>
        </tables_to_cache>
        <tables_to_cache_nchunks type="dictionary">
          <gridcells type="integer">1</gridcells>
        </tables_to_cache_nchunks>
        <tables_to_copy_to_previous_years type="dictionary">
          <development_type_group_definitions type="integer">1975</development_type_group_definitions>
          <development_type_groups type="integer">1975</development_type_groups>
          <development_types type="integer">1975</development_types>
          <development_constraints type="integer">1975</development_constraints>
          <urbansim_constants type="integer">1975</urbansim_constants>
        </tables_to_copy_to_previous_years>
      </creating_baseyear_cache_configuration>
      <dataset_pool_configuration type="class">
        <Class_name hidden="True" type="string">DatasetPoolConfiguration</Class_name>
        <Class_path hidden="True" type="string">opus_core.configurations.dataset_pool_configuration</Class_path>
        <package_order type="list">['eugene', 'urbansim', 'opus_core']</package_order>
      </dataset_pool_configuration>
    </Eugene_baseline>
  </scenario_manager>
  <results_manager>
    <Indicator_batches setexpanded="True" type="group" />
    <Simulation_runs followers="Results" setexpanded="True" type="all_source_data">
      <base_year_data type="source_data">
        <end_year hidden="True" type="integer">1980</end_year>
        <start_year hidden="True" type="integer">1980</start_year>
        <cache_directory hidden="True" type="string">/Users/christofferklang/Documents/workspace/Opus/data/eugene_gridcell/base_year_data</cache_directory>
        <run_name hidden="True" type="string">base_year_data</run_name>
        <scenario_name hidden="True" type="string">eugene_gridcell</scenario_name>
        <run_id hidden="True" type="integer">105</run_id>
      </base_year_data>
    </Simulation_runs>
  </results_manager>
</opus_project>